{
    "players": [
        {
            "index": 45,
            "cid": 65006,
            "title": "T4 Ep. 11 - Legend LF Josh Devore NY1 1910",
            "value": 72,
            "price": 382,
            "pa": 33874,
            "war": 4.4157761115,
            "avg": 0.3091730714,
            "obp": 0.4180492413,
            "slg": 0.5061912895,
            "ops": 0.9242405308,
            "hr": 8.5198087028,
            "kp": 0.0648580032,
            "bbp": 0.1581448899,
            "bbpk": 2.4383249886,
            "sbp": null,
            "sb": 25.2405975084,
            "woba": 0.4041793927,
            "normWar": 1.0,
            "warRank": 1.0,
            "paRank": 1.0,
            "avgRank": 2.0,
            "obpRank": 1.0,
            "slgRank": 3.0,
            "opsRank": 2.0,
            "hrRank": 10.0,
            "kRank": 10.0,
            "bbRank": 3.0,
            "bbpkRank": 4.0,
            "sbpRank": 1.0,
            "sbRank": 2.0,
            "wobaRank": 2.0,
            "contact": 97,
            "gap": 74,
            "power": 70,
            "eye": 120,
            "avoidk": 77,
            "babip": 106,
            "contactvL": 62,
            "gapvL": 62,
            "powervL": 48,
            "eyevL": 114,
            "avoidkvL": 44,
            "babipvL": 82,
            "contactvR": 111,
            "gapvr": 77,
            "powervR": 77,
            "eyevR": 123,
            "avoidkvR": 89,
            "babipvR": 115,
            "gbProfile": 1,
            "fbProfile": 1,
            "batterProfile": 0,
            "speed": 93,
            "stealRate": 85,
            "stealing": 103,
            "baserunning": 89,
            "sacBunt": 58,
            "buntForHit": 54,
            "catchAbil": 0,
            "catchFrame": 0,
            "catchArm": 0,
            "infRange": 8,
            "infError": 10,
            "infArm": 2,
            "dp": 5,
            "outfRange": 71,
            "outfError": 61,
            "outfArm": 97
        },
        {
            "index": 47,
            "cid": 67928,
            "title": "Tournament Edition 4 RF Sam Crawford CIN 1901",
            "value": 74,
            "price": 7085,
            "pa": 9636,
            "war": 3.5678704857,
            "avg": 0.3122651179,
            "obp": 0.3599003736,
            "slg": 0.6206582394,
            "ops": 0.980558613,
            "hr": 23.2254047323,
            "kp": 0.0832295558,
            "bbp": 0.0713989207,
            "bbpk": 0.8578553616,
            "sbp": null,
            "sb": 3.8605230386,
            "woba": 0.4193349494,
            "normWar": 0.8890441196,
            "warRank": 2.0,
            "paRank": 6.0,
            "avgRank": 1.0,
            "obpRank": 7.0,
            "slgRank": 1.0,
            "opsRank": 1.0,
            "hrRank": 1.0,
            "kRank": 15.0,
            "bbRank": 17.0,
            "bbpkRank": 18.0,
            "sbpRank": 2.0,
            "sbRank": 13.0,
            "wobaRank": 1.0,
            "contact": 91,
            "gap": 108,
            "power": 128,
            "eye": 64,
            "avoidk": 77,
            "babip": 96,
            "contactvL": 85,
            "gapvL": 103,
            "powervL": 137,
            "eyevL": 51,
            "avoidkvL": 74,
            "babipvL": 92,
            "contactvR": 93,
            "gapvr": 110,
            "powervR": 125,
            "eyevR": 69,
            "avoidkvR": 78,
            "babipvR": 98,
            "gbProfile": 2,
            "fbProfile": 1,
            "batterProfile": 0,
            "speed": 71,
            "stealRate": 79,
            "stealing": 77,
            "baserunning": 66,
            "sacBunt": 18,
            "buntForHit": 90,
            "catchAbil": 0,
            "catchFrame": 0,
            "catchArm": 0,
            "infRange": 1,
            "infError": 2,
            "infArm": 3,
            "dp": 3,
            "outfRange": 69,
            "outfError": 48,
            "outfArm": 78
        },
        {
            "index": 40,
            "cid": 67737,
            "title": "In the Deadball of Winter - Unsung Heroes RF Steve Evans STL 1911",
            "value": 66,
            "price": 406,
            "pa": 759,
            "war": 2.766798419,
            "avg": 0.3060029283,
            "obp": 0.3583662714,
            "slg": 0.5109809663,
            "ops": 0.8693472377,
            "hr": 10.2766798419,
            "kp": 0.0619235837,
            "bbp": 0.0737812912,
            "bbpk": 1.1914893617,
            "sbp": null,
            "sb": 7.1146245059,
            "woba": 0.3740079365,
            "normWar": 0.7842168208,
            "warRank": 3.0,
            "paRank": 20.0,
            "avgRank": 4.0,
            "obpRank": 8.0,
            "slgRank": 2.0,
            "opsRank": 3.0,
            "hrRank": 7.0,
            "kRank": 7.0,
            "bbRank": 16.0,
            "bbpkRank": 15.0,
            "sbpRank": 3.0,
            "sbRank": 9.0,
            "wobaRank": 3.0,
            "contact": 97,
            "gap": 86,
            "power": 77,
            "eye": 73,
            "avoidk": 87,
            "babip": 95,
            "contactvL": 79,
            "gapvL": 64,
            "powervL": 52,
            "eyevL": 81,
            "avoidkvL": 69,
            "babipvL": 90,
            "contactvR": 103,
            "gapvr": 97,
            "powervR": 88,
            "eyevR": 70,
            "avoidkvR": 96,
            "babipvR": 97,
            "gbProfile": 2,
            "fbProfile": 1,
            "batterProfile": 0,
            "speed": 65,
            "stealRate": 80,
            "stealing": 83,
            "baserunning": 72,
            "sacBunt": 51,
            "buntForHit": 49,
            "catchAbil": 0,
            "catchFrame": 0,
            "catchArm": 0,
            "infRange": 48,
            "infError": 52,
            "infArm": 44,
            "dp": 53,
            "outfRange": 92,
            "outfError": 89,
            "outfArm": 69
        },
        {
            "index": 21,
            "cid": 67332,
            "title": "T4 Ep. 7 - Hardware Heroes RF Mike Mitchell CIN 1911",
            "value": 71,
            "price": 252,
            "pa": 22796,
            "war": 2.5715037726,
            "avg": 0.2804328224,
            "obp": 0.3238726092,
            "slg": 0.4755350956,
            "ops": 0.7994077049,
            "hr": 7.106509914,
            "kp": 0.0388226005,
            "bbp": 0.0600543955,
            "bbpk": 1.5468926554,
            "sbp": null,
            "sb": 9.3437445166,
            "woba": 0.3463874253,
            "normWar": 0.7586608052,
            "warRank": 4.0,
            "paRank": 5.0,
            "avgRank": 13.0,
            "obpRank": 18.0,
            "slgRank": 5.0,
            "opsRank": 7.0,
            "hrRank": 11.0,
            "kRank": 2.0,
            "bbRank": 19.0,
            "bbpkRank": 10.0,
            "sbpRank": 4.0,
            "sbRank": 7.0,
            "wobaRank": 7.0,
            "contact": 99,
            "gap": 98,
            "power": 75,
            "eye": 57,
            "avoidk": 122,
            "babip": 76,
            "contactvL": 119,
            "gapvL": 102,
            "powervL": 77,
            "eyevL": 84,
            "avoidkvL": 138,
            "babipvL": 98,
            "contactvR": 92,
            "gapvr": 97,
            "powervR": 75,
            "eyevR": 48,
            "avoidkvR": 118,
            "babipvR": 71,
            "gbProfile": 0,
            "fbProfile": 2,
            "batterProfile": 0,
            "speed": 104,
            "stealRate": 85,
            "stealing": 91,
            "baserunning": 113,
            "sacBunt": 93,
            "buntForHit": 82,
            "catchAbil": 0,
            "catchFrame": 0,
            "catchArm": 0,
            "infRange": 9,
            "infError": 10,
            "infArm": 2,
            "dp": 1,
            "outfRange": 105,
            "outfError": 106,
            "outfArm": 98
        },
        {
            "index": 15,
            "cid": 64697,
            "title": "NeL Set 4 - Negro League Star C Bruce Petway Detroit Stars 1923",
            "value": 74,
            "price": 404,
            "pa": 29912,
            "war": 2.5494784702,
            "avg": 0.293131827,
            "obp": 0.3554426317,
            "slg": 0.3848945085,
            "ops": 0.7403371402,
            "hr": 4.4530623161,
            "kp": 0.0388807168,
            "bbp": 0.0896630115,
            "bbpk": 2.3061049011,
            "sbp": 0.1285535491,
            "sb": 14.4223054293,
            "woba": 0.3306794747,
            "normWar": 0.7557786014,
            "warRank": 5.0,
            "paRank": 2.0,
            "avgRank": 7.0,
            "obpRank": 12.0,
            "slgRank": 12.0,
            "opsRank": 13.0,
            "hrRank": 16.0,
            "kRank": 3.0,
            "bbRank": 13.0,
            "bbpkRank": 6.0,
            "sbpRank": 14.0,
            "sbRank": 3.0,
            "wobaRank": 14.0,
            "contact": 110,
            "gap": 66,
            "power": 50,
            "eye": 78,
            "avoidk": 116,
            "babip": 91,
            "contactvL": 110,
            "gapvL": 69,
            "powervL": 54,
            "eyevL": 82,
            "avoidkvL": 115,
            "babipvL": 93,
            "contactvR": 109,
            "gapvr": 66,
            "powervR": 48,
            "eyevR": 78,
            "avoidkvR": 117,
            "babipvR": 90,
            "gbProfile": 0,
            "fbProfile": 0,
            "batterProfile": 0,
            "speed": 86,
            "stealRate": 51,
            "stealing": 92,
            "baserunning": 95,
            "sacBunt": 97,
            "buntForHit": 100,
            "catchAbil": 106,
            "catchFrame": 109,
            "catchArm": 107,
            "infRange": 29,
            "infError": 29,
            "infArm": 28,
            "dp": 27,
            "outfRange": 74,
            "outfError": 59,
            "outfArm": 59
        },
        {
            "index": 27,
            "cid": 64637,
            "title": "T4 Ep. 2 - Negro League Star 3B Kid Lowe Memphis Red Sox Peak",
            "value": 71,
            "price": 364,
            "pa": 24540,
            "war": 2.3227383863,
            "avg": 0.3036872249,
            "obp": 0.3908720456,
            "slg": 0.3410801344,
            "ops": 0.7319521801,
            "hr": 0.7579462103,
            "kp": 0.0494295029,
            "bbp": 0.1258761206,
            "bbpk": 2.5465787304,
            "sbp": 3.0985915493,
            "sb": 5.3789731051,
            "woba": 0.3352808208,
            "normWar": 0.7261076747,
            "warRank": 6.0,
            "paRank": 3.0,
            "avgRank": 6.0,
            "obpRank": 2.0,
            "slgRank": 18.0,
            "opsRank": 14.0,
            "hrRank": 18.0,
            "kRank": 5.0,
            "bbRank": 6.0,
            "bbpkRank": 2.0,
            "sbpRank": 13.0,
            "sbRank": 11.0,
            "wobaRank": 11.0,
            "contact": 115,
            "gap": 34,
            "power": 13,
            "eye": 101,
            "avoidk": 104,
            "babip": 112,
            "contactvL": 117,
            "gapvL": 38,
            "powervL": 25,
            "eyevL": 102,
            "avoidkvL": 108,
            "babipvL": 113,
            "contactvR": 115,
            "gapvr": 33,
            "powervR": 10,
            "eyevR": 101,
            "avoidkvR": 103,
            "babipvR": 112,
            "gbProfile": 0,
            "fbProfile": 2,
            "batterProfile": 1,
            "speed": 65,
            "stealRate": 34,
            "stealing": 70,
            "baserunning": 51,
            "sacBunt": 103,
            "buntForHit": 100,
            "catchAbil": 56,
            "catchFrame": 58,
            "catchArm": 59,
            "infRange": 85,
            "infError": 64,
            "infArm": 82,
            "dp": 76,
            "outfRange": 78,
            "outfError": 68,
            "outfArm": 64
        },
        {
            "index": 9,
            "cid": 64743,
            "title": "Early Eras - Negro League Star CF Orville Singer Cleveland Tigers 1928",
            "value": 66,
            "price": 148,
            "pa": 7562,
            "war": 2.308912986,
            "avg": 0.3088707324,
            "obp": 0.3602221634,
            "slg": 0.4463087248,
            "ops": 0.8065308883,
            "hr": 13.1711187517,
            "kp": 0.0653266332,
            "bbp": 0.0763025655,
            "bbpk": 1.1680161943,
            "sbp": null,
            "sb": 3.6498280878,
            "woba": 0.3544199628,
            "normWar": 0.7242985,
            "warRank": 7.0,
            "paRank": 7.0,
            "avgRank": 3.0,
            "obpRank": 6.0,
            "slgRank": 6.0,
            "opsRank": 5.0,
            "hrRank": 4.0,
            "kRank": 11.0,
            "bbRank": 15.0,
            "bbpkRank": 16.0,
            "sbpRank": 5.0,
            "sbRank": 14.0,
            "wobaRank": 6.0,
            "contact": 101,
            "gap": 47,
            "power": 86,
            "eye": 70,
            "avoidk": 86,
            "babip": 102,
            "contactvL": 103,
            "gapvL": 49,
            "powervL": 89,
            "eyevL": 71,
            "avoidkvL": 88,
            "babipvL": 103,
            "contactvR": 101,
            "gapvr": 47,
            "powervR": 86,
            "eyevR": 70,
            "avoidkvR": 86,
            "babipvR": 102,
            "gbProfile": 0,
            "fbProfile": 1,
            "batterProfile": 0,
            "speed": 63,
            "stealRate": 60,
            "stealing": 78,
            "baserunning": 59,
            "sacBunt": 84,
            "buntForHit": 96,
            "catchAbil": 1,
            "catchFrame": 1,
            "catchArm": 1,
            "infRange": 74,
            "infError": 62,
            "infArm": 68,
            "dp": 72,
            "outfRange": 74,
            "outfError": 59,
            "outfArm": 59
        },
        {
            "index": 44,
            "cid": 64543,
            "title": "NeL Set 1 - Negro League Star C Frank Duncan Kansas City Monarchs 1929",
            "value": 71,
            "price": 396,
            "pa": 5140,
            "war": 2.2529182879,
            "avg": 0.2892801426,
            "obp": 0.3680933852,
            "slg": 0.3775351014,
            "ops": 0.7456284866,
            "hr": 2.2178988327,
            "kp": 0.0675097276,
            "bbp": 0.1134241245,
            "bbpk": 1.6801152738,
            "sbp": 0.0343891403,
            "sb": 4.4357976654,
            "woba": 0.336377891,
            "normWar": 0.7169711031,
            "warRank": 8.0,
            "paRank": 9.0,
            "avgRank": 8.0,
            "obpRank": 3.0,
            "slgRank": 13.0,
            "opsRank": 12.0,
            "hrRank": 17.0,
            "kRank": 12.0,
            "bbRank": 7.0,
            "bbpkRank": 8.0,
            "sbpRank": 17.0,
            "sbRank": 12.0,
            "wobaRank": 10.0,
            "contact": 92,
            "gap": 80,
            "power": 31,
            "eye": 89,
            "avoidk": 78,
            "babip": 97,
            "contactvL": 88,
            "gapvL": 71,
            "powervL": 25,
            "eyevL": 86,
            "avoidkvL": 75,
            "babipvL": 96,
            "contactvR": 95,
            "gapvr": 86,
            "powervR": 33,
            "eyevR": 90,
            "avoidkvR": 80,
            "babipvR": 98,
            "gbProfile": 0,
            "fbProfile": 1,
            "batterProfile": 1,
            "speed": 59,
            "stealRate": 56,
            "stealing": 77,
            "baserunning": 58,
            "sacBunt": 94,
            "buntForHit": 98,
            "catchAbil": 89,
            "catchFrame": 93,
            "catchArm": 96,
            "infRange": 47,
            "infError": 31,
            "infArm": 39,
            "dp": 29,
            "outfRange": 74,
            "outfError": 59,
            "outfArm": 59
        },
        {
            "index": 39,
            "cid": 67662,
            "title": "T4 Ep. 12 - Snapshot RF Jim Fogarty PHI 1887",
            "value": 69,
            "price": 122,
            "pa": 2877,
            "war": 2.1897810219,
            "avg": 0.231191885,
            "obp": 0.3580118179,
            "slg": 0.3613693998,
            "ops": 0.7193812177,
            "hr": 12.0959332638,
            "kp": 0.0914146681,
            "bbp": 0.1637122002,
            "bbpk": 1.7908745247,
            "sbp": null,
            "sb": 10.2189781022,
            "woba": 0.3291010843,
            "normWar": 0.7087090386,
            "warRank": 9.0,
            "paRank": 12.0,
            "avgRank": 17.0,
            "obpRank": 10.0,
            "slgRank": 15.0,
            "opsRank": 15.0,
            "hrRank": 5.0,
            "kRank": 17.0,
            "bbRank": 1.0,
            "bbpkRank": 7.0,
            "sbpRank": 6.0,
            "sbRank": 6.0,
            "wobaRank": 15.0,
            "contact": 59,
            "gap": 95,
            "power": 87,
            "eye": 118,
            "avoidk": 70,
            "babip": 55,
            "contactvL": 71,
            "gapvL": 101,
            "powervL": 91,
            "eyevL": 123,
            "avoidkvL": 73,
            "babipvL": 69,
            "contactvR": 56,
            "gapvr": 93,
            "powervR": 86,
            "eyevR": 117,
            "avoidkvR": 69,
            "babipvR": 50,
            "gbProfile": 0,
            "fbProfile": 0,
            "batterProfile": 0,
            "speed": 82,
            "stealRate": 89,
            "stealing": 100,
            "baserunning": 91,
            "sacBunt": 5,
            "buntForHit": 1,
            "catchAbil": 0,
            "catchFrame": 0,
            "catchArm": 0,
            "infRange": 10,
            "infError": 8,
            "infArm": 4,
            "dp": 10,
            "outfRange": 101,
            "outfError": 81,
            "outfArm": 108
        },
        {
            "index": 8,
            "cid": 65431,
            "title": "T4 Ep. 1 - Snapshot LF Elmer Smith PIT 1897",
            "value": 67,
            "price": 68,
            "pa": 2713,
            "war": 2.1673424254,
            "avg": 0.260756193,
            "obp": 0.3582749724,
            "slg": 0.5032594524,
            "ops": 0.8615344248,
            "hr": 16.5868042757,
            "kp": 0.1057869517,
            "bbp": 0.1341688168,
            "bbpk": 1.2682926829,
            "sbp": null,
            "sb": 1.7692591227,
            "woba": 0.3715982242,
            "normWar": 0.7057727517,
            "warRank": 10.0,
            "paRank": 13.0,
            "avgRank": 15.0,
            "obpRank": 9.0,
            "slgRank": 4.0,
            "opsRank": 4.0,
            "hrRank": 2.0,
            "kRank": 18.0,
            "bbRank": 5.0,
            "bbpkRank": 14.0,
            "sbpRank": 7.0,
            "sbRank": 17.0,
            "wobaRank": 4.0,
            "contact": 62,
            "gap": 100,
            "power": 100,
            "eye": 107,
            "avoidk": 55,
            "babip": 74,
            "contactvL": 58,
            "gapvL": 98,
            "powervL": 97,
            "eyevL": 104,
            "avoidkvL": 52,
            "babipvL": 72,
            "contactvR": 63,
            "gapvr": 101,
            "powervR": 101,
            "eyevR": 108,
            "avoidkvR": 56,
            "babipvR": 75,
            "gbProfile": 1,
            "fbProfile": 0,
            "batterProfile": 0,
            "speed": 65,
            "stealRate": 61,
            "stealing": 65,
            "baserunning": 55,
            "sacBunt": 53,
            "buntForHit": 34,
            "catchAbil": 0,
            "catchFrame": 0,
            "catchArm": 0,
            "infRange": 5,
            "infError": 9,
            "infArm": 9,
            "dp": 9,
            "outfRange": 66,
            "outfError": 40,
            "outfArm": 68
        },
        {
            "index": 0,
            "cid": 65443,
            "title": "September Studs - Snapshot RF Taffy Wright CWS 1941",
            "value": 72,
            "price": 364,
            "pa": 23739,
            "war": 1.8071527866,
            "avg": 0.3043989649,
            "obp": 0.3651796622,
            "slg": 0.440649259,
            "ops": 0.8058289212,
            "hr": 5.7121192974,
            "kp": 0.0360588062,
            "bbp": 0.0887147732,
            "bbpk": 2.4602803738,
            "sbp": null,
            "sb": 1.7439656262,
            "woba": 0.3548767993,
            "normWar": 0.6586387815,
            "warRank": 11.0,
            "paRank": 4.0,
            "avgRank": 5.0,
            "obpRank": 5.0,
            "slgRank": 7.0,
            "opsRank": 6.0,
            "hrRank": 14.0,
            "kRank": 1.0,
            "bbRank": 14.0,
            "bbpkRank": 3.0,
            "sbpRank": 8.0,
            "sbRank": 18.0,
            "wobaRank": 5.0,
            "contact": 119,
            "gap": 104,
            "power": 61,
            "eye": 76,
            "avoidk": 125,
            "babip": 104,
            "contactvL": 119,
            "gapvL": 101,
            "powervL": 22,
            "eyevL": 60,
            "avoidkvL": 110,
            "babipvL": 114,
            "contactvR": 119,
            "gapvr": 105,
            "powervR": 71,
            "eyevR": 80,
            "avoidkvR": 131,
            "babipvR": 101,
            "gbProfile": 3,
            "fbProfile": 1,
            "batterProfile": 0,
            "speed": 63,
            "stealRate": 50,
            "stealing": 62,
            "baserunning": 74,
            "sacBunt": 11,
            "buntForHit": 6,
            "catchAbil": 0,
            "catchFrame": 0,
            "catchArm": 0,
            "infRange": 4,
            "infError": 1,
            "infArm": 4,
            "dp": 9,
            "outfRange": 74,
            "outfError": 81,
            "outfArm": 59
        },
        {
            "index": 3,
            "cid": 66697,
            "title": "NeL Set 3 - Negro League Star CF David Whatley Birmingham Black Barons 1937",
            "value": 74,
            "price": 460,
            "pa": 5498,
            "war": 1.7460894871,
            "avg": 0.2864167179,
            "obp": 0.3575845762,
            "slg": 0.4005326777,
            "ops": 0.7581172539,
            "hr": 4.8017460895,
            "kp": 0.0720261913,
            "bbp": 0.0994907239,
            "bbpk": 1.3813131313,
            "sbp": null,
            "sb": 30.8839578028,
            "woba": 0.3380800878,
            "normWar": 0.6506481137,
            "warRank": 12.0,
            "paRank": 8.0,
            "avgRank": 9.0,
            "obpRank": 11.0,
            "slgRank": 11.0,
            "opsRank": 10.0,
            "hrRank": 15.0,
            "kRank": 14.0,
            "bbRank": 10.0,
            "bbpkRank": 13.0,
            "sbpRank": 9.0,
            "sbRank": 1.0,
            "wobaRank": 9.0,
            "contact": 92,
            "gap": 78,
            "power": 55,
            "eye": 79,
            "avoidk": 85,
            "babip": 90,
            "contactvL": 90,
            "gapvL": 75,
            "powervL": 55,
            "eyevL": 72,
            "avoidkvL": 83,
            "babipvL": 88,
            "contactvR": 94,
            "gapvr": 80,
            "powervR": 56,
            "eyevR": 84,
            "avoidkvR": 86,
            "babipvR": 91,
            "gbProfile": 2,
            "fbProfile": 1,
            "batterProfile": 0,
            "speed": 97,
            "stealRate": 82,
            "stealing": 104,
            "baserunning": 106,
            "sacBunt": 28,
            "buntForHit": 35,
            "catchAbil": 1,
            "catchFrame": 1,
            "catchArm": 1,
            "infRange": 4,
            "infError": 4,
            "infArm": 11,
            "dp": 4,
            "outfRange": 78,
            "outfError": 67,
            "outfArm": 83
        },
        {
            "index": 51,
            "cid": 65481,
            "title": "T4 Ep. 2 - Snapshot SP Ray Caldwell NYY 1918",
            "value": 69,
            "price": 100,
            "pa": 1271,
            "war": 1.3690007868,
            "avg": 0.2855879752,
            "obp": 0.3501180173,
            "slg": 0.4031830239,
            "ops": 0.7533010412,
            "hr": 6.1369000787,
            "kp": 0.1266719119,
            "bbp": 0.0920535012,
            "bbpk": 0.7267080745,
            "sbp": 0.0041666667,
            "sb": 0.4720692368,
            "woba": 0.3334357762,
            "normWar": 0.6013027533,
            "warRank": 13.0,
            "paRank": 17.0,
            "avgRank": 10.0,
            "obpRank": 14.0,
            "slgRank": 10.0,
            "opsRank": 11.0,
            "hrRank": 12.0,
            "kRank": 20.0,
            "bbRank": 12.0,
            "bbpkRank": 19.0,
            "sbpRank": 19.0,
            "sbRank": 19.0,
            "wobaRank": 12.0,
            "contact": 75,
            "gap": 120,
            "power": 76,
            "eye": 70,
            "avoidk": 54,
            "babip": 101,
            "contactvL": 100,
            "gapvL": 146,
            "powervL": 42,
            "eyevL": 64,
            "avoidkvL": 77,
            "babipvL": 110,
            "contactvR": 68,
            "gapvr": 114,
            "powervR": 88,
            "eyevR": 73,
            "avoidkvR": 43,
            "babipvR": 98,
            "gbProfile": 2,
            "fbProfile": 2,
            "batterProfile": 0,
            "speed": 31,
            "stealRate": 58,
            "stealing": 54,
            "baserunning": 37,
            "sacBunt": 24,
            "buntForHit": 1,
            "catchAbil": 0,
            "catchFrame": 0,
            "catchArm": 0,
            "infRange": 25,
            "infError": 36,
            "infArm": 28,
            "dp": 24,
            "outfRange": 69,
            "outfError": 56,
            "outfArm": 65
        },
        {
            "index": 4,
            "cid": 67714,
            "title": "In the Deadball of Winter - Super Util 2B Piggy Ward WAS 1894",
            "value": 61,
            "price": 628,
            "pa": 1167,
            "war": 1.1311053985,
            "avg": 0.2437759336,
            "obp": 0.3676092545,
            "slg": 0.3454356846,
            "ops": 0.7130449391,
            "hr": 0.5141388175,
            "kp": 0.1062553556,
            "bbp": 0.1619537275,
            "bbpk": 1.5241935484,
            "sbp": null,
            "sb": 13.881748072,
            "woba": 0.3268303187,
            "normWar": 0.5701720573,
            "warRank": 14.0,
            "paRank": 19.0,
            "avgRank": 16.0,
            "obpRank": 4.0,
            "slgRank": 17.0,
            "opsRank": 16.0,
            "hrRank": 19.0,
            "kRank": 19.0,
            "bbRank": 2.0,
            "bbpkRank": 11.0,
            "sbpRank": 10.0,
            "sbRank": 5.0,
            "wobaRank": 16.0,
            "contact": 79,
            "gap": 73,
            "power": 9,
            "eye": 137,
            "avoidk": 66,
            "babip": 95,
            "contactvL": 80,
            "gapvL": 73,
            "powervL": 11,
            "eyevL": 134,
            "avoidkvL": 66,
            "babipvL": 97,
            "contactvR": 80,
            "gapvr": 74,
            "powervR": 9,
            "eyevR": 138,
            "avoidkvR": 67,
            "babipvR": 95,
            "gbProfile": 1,
            "fbProfile": 0,
            "batterProfile": 0,
            "speed": 84,
            "stealRate": 86,
            "stealing": 102,
            "baserunning": 89,
            "sacBunt": 70,
            "buntForHit": 62,
            "catchAbil": 0,
            "catchFrame": 0,
            "catchArm": 0,
            "infRange": 83,
            "infError": 70,
            "infArm": 66,
            "dp": 75,
            "outfRange": 72,
            "outfError": 67,
            "outfArm": 69
        },
        {
            "index": 53,
            "cid": 63170,
            "title": "Snapshot RF Ike Boone BOS 1924",
            "value": 74,
            "price": 208,
            "pa": 2174,
            "war": 0.7451701932,
            "avg": 0.2809573361,
            "obp": 0.353725851,
            "slg": 0.4120707596,
            "ops": 0.7657966106,
            "hr": 11.5915363385,
            "kp": 0.0717571297,
            "bbp": 0.1034958602,
            "bbpk": 1.4423076923,
            "sbp": null,
            "sb": 1.9319227231,
            "woba": 0.3422758941,
            "normWar": 0.5196690542,
            "warRank": 15.0,
            "paRank": 16.0,
            "avgRank": 12.0,
            "obpRank": 13.0,
            "slgRank": 9.0,
            "opsRank": 8.0,
            "hrRank": 6.0,
            "kRank": 13.0,
            "bbRank": 9.0,
            "bbpkRank": 12.0,
            "sbpRank": 11.0,
            "sbRank": 16.0,
            "wobaRank": 8.0,
            "contact": 77,
            "gap": 76,
            "power": 90,
            "eye": 77,
            "avoidk": 76,
            "babip": 77,
            "contactvL": 68,
            "gapvL": 66,
            "powervL": 105,
            "eyevL": 64,
            "avoidkvL": 63,
            "babipvL": 74,
            "contactvR": 81,
            "gapvr": 79,
            "powervR": 85,
            "eyevR": 80,
            "avoidkvR": 79,
            "babipvR": 79,
            "gbProfile": 0,
            "fbProfile": 0,
            "batterProfile": 0,
            "speed": 27,
            "stealRate": 11,
            "stealing": 57,
            "baserunning": 30,
            "sacBunt": 13,
            "buntForHit": 8,
            "catchAbil": 0,
            "catchFrame": 0,
            "catchArm": 0,
            "infRange": 2,
            "infError": 8,
            "infArm": 8,
            "dp": 10,
            "outfRange": 47,
            "outfError": 83,
            "outfArm": 84
        },
        {
            "index": 50,
            "cid": 67728,
            "title": "T4 Ep. 13 - Snapshot SP Bob Caruthers BR3 1888",
            "value": 74,
            "price": 673,
            "pa": 4312,
            "war": 0.5705009276,
            "avg": 0.2254575707,
            "obp": 0.3392857143,
            "slg": 0.3580144204,
            "ops": 0.6973001347,
            "hr": 14.332096475,
            "kp": 0.0514842301,
            "bbp": 0.1461038961,
            "bbpk": 2.8378378378,
            "sbp": 0.0526315789,
            "sb": 6.6790352505,
            "woba": 0.3163249651,
            "normWar": 0.4968120504,
            "warRank": 16.0,
            "paRank": 10.0,
            "avgRank": 18.0,
            "obpRank": 16.0,
            "slgRank": 16.0,
            "opsRank": 18.0,
            "hrRank": 3.0,
            "kRank": 6.0,
            "bbRank": 4.0,
            "bbpkRank": 1.0,
            "sbpRank": 15.0,
            "sbRank": 10.0,
            "wobaRank": 18.0,
            "contact": 66,
            "gap": 69,
            "power": 89,
            "eye": 112,
            "avoidk": 106,
            "babip": 42,
            "contactvL": 64,
            "gapvL": 69,
            "powervL": 85,
            "eyevL": 108,
            "avoidkvL": 102,
            "babipvL": 42,
            "contactvR": 67,
            "gapvr": 70,
            "powervR": 90,
            "eyevR": 114,
            "avoidkvR": 108,
            "babipvR": 43,
            "gbProfile": 2,
            "fbProfile": 1,
            "batterProfile": 0,
            "speed": 70,
            "stealRate": 93,
            "stealing": 88,
            "baserunning": 67,
            "sacBunt": 7,
            "buntForHit": 8,
            "catchAbil": 0,
            "catchFrame": 0,
            "catchArm": 0,
            "infRange": 30,
            "infError": 37,
            "infArm": 31,
            "dp": 27,
            "outfRange": 73,
            "outfError": 57,
            "outfArm": 56
        },
        {
            "index": 55,
            "cid": 64462,
            "title": "NeL Set 2 - Negro League Star RF Bill Bea Philadelphia Stars 1940",
            "value": 71,
            "price": 387,
            "pa": 1181,
            "war": 0.5080440305,
            "avg": 0.2836363636,
            "obp": 0.3276883997,
            "slg": 0.4318181818,
            "ops": 0.7595065815,
            "hr": 9.6528365792,
            "kp": 0.083827265,
            "bbp": 0.0558848434,
            "bbpk": 0.6666666667,
            "sbp": 0.0,
            "sb": 0.0,
            "woba": 0.3326440678,
            "normWar": 0.4886390182,
            "warRank": 17.0,
            "paRank": 18.0,
            "avgRank": 11.0,
            "obpRank": 17.0,
            "slgRank": 8.0,
            "opsRank": 9.0,
            "hrRank": 8.0,
            "kRank": 16.0,
            "bbRank": 20.0,
            "bbpkRank": 20.0,
            "sbpRank": 20.0,
            "sbRank": 20.0,
            "wobaRank": 13.0,
            "contact": 103,
            "gap": 112,
            "power": 66,
            "eye": 62,
            "avoidk": 83,
            "babip": 107,
            "contactvL": 106,
            "gapvL": 116,
            "powervL": 69,
            "eyevL": 67,
            "avoidkvL": 84,
            "babipvL": 111,
            "contactvR": 102,
            "gapvr": 111,
            "powervR": 66,
            "eyevR": 61,
            "avoidkvR": 83,
            "babipvR": 106,
            "gbProfile": 0,
            "fbProfile": 0,
            "batterProfile": 0,
            "speed": 29,
            "stealRate": 9,
            "stealing": 6,
            "baserunning": 29,
            "sacBunt": 16,
            "buntForHit": 11,
            "catchAbil": 1,
            "catchFrame": 1,
            "catchArm": 1,
            "infRange": 25,
            "infError": 21,
            "infArm": 22,
            "dp": 20,
            "outfRange": 58,
            "outfError": 62,
            "outfArm": 67
        },
        {
            "index": 32,
            "cid": 66831,
            "title": "Food for Thought - Unsung Heroes CF Paul Hines IN3 1889",
            "value": 71,
            "price": 391,
            "pa": 2344,
            "war": -0.2303754266,
            "avg": 0.2719382835,
            "obp": 0.3447098976,
            "slg": 0.3635486982,
            "ops": 0.7082585958,
            "hr": 5.8873720137,
            "kp": 0.042662116,
            "bbp": 0.0989761092,
            "bbpk": 2.32,
            "sbp": null,
            "sb": 14.3344709898,
            "woba": 0.320172043,
            "normWar": 0.3920103623,
            "warRank": 18.0,
            "paRank": 15.0,
            "avgRank": 14.0,
            "obpRank": 15.0,
            "slgRank": 14.0,
            "opsRank": 17.0,
            "hrRank": 13.0,
            "kRank": 4.0,
            "bbRank": 11.0,
            "bbpkRank": 5.0,
            "sbpRank": 12.0,
            "sbRank": 4.0,
            "wobaRank": 17.0,
            "contact": 102,
            "gap": 87,
            "power": 70,
            "eye": 77,
            "avoidk": 118,
            "babip": 79,
            "contactvL": 107,
            "gapvL": 91,
            "powervL": 74,
            "eyevL": 80,
            "avoidkvL": 122,
            "babipvL": 84,
            "contactvR": 100,
            "gapvr": 86,
            "powervR": 69,
            "eyevR": 77,
            "avoidkvR": 117,
            "babipvR": 78,
            "gbProfile": 0,
            "fbProfile": 0,
            "batterProfile": 0,
            "speed": 67,
            "stealRate": 89,
            "stealing": 88,
            "baserunning": 76,
            "sacBunt": 51,
            "buntForHit": 65,
            "catchAbil": 0,
            "catchFrame": 0,
            "catchArm": 0,
            "infRange": 56,
            "infError": 57,
            "infArm": 58,
            "dp": 54,
            "outfRange": 65,
            "outfError": 59,
            "outfArm": 60
        },
        {
            "index": 28,
            "cid": 68008,
            "title": "Tournament Edition 4 SP Silver King SL4 1887",
            "value": 74,
            "price": 6435,
            "pa": 3671,
            "war": -1.2421683465,
            "avg": 0.2129773362,
            "obp": 0.2941977663,
            "slg": 0.2846941943,
            "ops": 0.5788919606,
            "hr": 0.1634432035,
            "kp": 0.0621084173,
            "bbp": 0.1043312449,
            "bbpk": 1.6798245614,
            "sbp": 0.0469404862,
            "sb": 9.1528193953,
            "woba": 0.2641019351,
            "normWar": 0.2596083935,
            "warRank": 19.0,
            "paRank": 11.0,
            "avgRank": 19.0,
            "obpRank": 19.0,
            "slgRank": 19.0,
            "opsRank": 19.0,
            "hrRank": 20.0,
            "kRank": 8.0,
            "bbRank": 8.0,
            "bbpkRank": 9.0,
            "sbpRank": 16.0,
            "sbRank": 8.0,
            "wobaRank": 19.0,
            "contact": 76,
            "gap": 82,
            "power": 20,
            "eye": 96,
            "avoidk": 105,
            "babip": 58,
            "contactvL": 84,
            "gapvL": 88,
            "powervL": 21,
            "eyevL": 102,
            "avoidkvL": 107,
            "babipvL": 69,
            "contactvR": 73,
            "gapvr": 80,
            "powervR": 20,
            "eyevR": 94,
            "avoidkvR": 104,
            "babipvR": 55,
            "gbProfile": 0,
            "fbProfile": 1,
            "batterProfile": 0,
            "speed": 72,
            "stealRate": 89,
            "stealing": 98,
            "baserunning": 76,
            "sacBunt": 5,
            "buntForHit": 1,
            "catchAbil": 0,
            "catchFrame": 0,
            "catchArm": 0,
            "infRange": 25,
            "infError": 37,
            "infArm": 26,
            "dp": 17,
            "outfRange": 74,
            "outfError": 56,
            "outfArm": 64
        },
        {
            "index": 49,
            "cid": 66123,
            "title": "T4 Ep. 21 - Snapshot SP Ice Box Chamberlain LS3 Peak",
            "value": 74,
            "price": 543,
            "pa": 2641,
            "war": -3.2260507384,
            "avg": 0.1915422886,
            "obp": 0.2487694055,
            "slg": 0.2798507463,
            "ops": 0.5286201518,
            "hr": 8.8602801969,
            "kp": 0.0636122681,
            "bbp": 0.0708065127,
            "bbpk": 1.1130952381,
            "sbp": 0.0161054173,
            "sb": 2.4990533889,
            "woba": 0.2384874905,
            "normWar": 0.0,
            "warRank": 20.0,
            "paRank": 14.0,
            "avgRank": 20.0,
            "obpRank": 20.0,
            "slgRank": 20.0,
            "opsRank": 20.0,
            "hrRank": 9.0,
            "kRank": 9.0,
            "bbRank": 18.0,
            "bbpkRank": 17.0,
            "sbpRank": 18.0,
            "sbRank": 15.0,
            "wobaRank": 20.0,
            "contact": 58,
            "gap": 69,
            "power": 72,
            "eye": 74,
            "avoidk": 89,
            "babip": 38,
            "contactvL": 66,
            "gapvL": 72,
            "powervL": 81,
            "eyevL": 75,
            "avoidkvL": 91,
            "babipvL": 51,
            "contactvR": 57,
            "gapvr": 69,
            "powervR": 69,
            "eyevR": 74,
            "avoidkvR": 88,
            "babipvR": 35,
            "gbProfile": 0,
            "fbProfile": 0,
            "batterProfile": 0,
            "speed": 76,
            "stealRate": 77,
            "stealing": 74,
            "baserunning": 70,
            "sacBunt": 78,
            "buntForHit": 62,
            "catchAbil": 0,
            "catchFrame": 0,
            "catchArm": 0,
            "infRange": 55,
            "infError": 59,
            "infArm": 69,
            "dp": 52,
            "outfRange": 74,
            "outfError": 69,
            "outfArm": 80
        }
    ]
}