{
    "players": [
        {
            "index": 0,
            "cid": 67061,
            "title": "Deadline Deals - Snapshot 2B Randy Velarde OAK 1999",
            "value": 79,
            "price": 499,
            "pa": 67261,
            "war": 2.7323411784,
            "avg": 0.3123394174,
            "obp": 0.3788673972,
            "slg": 0.4600420434,
            "ops": 0.8389094406,
            "hr": 10.6064435557,
            "kp": 0.1174826422,
            "bbp": 0.0952260597,
            "bbpk": 0.8105542901,
            "sbp": 0.5807692308,
            "sb": 10.7759325612,
            "woba": 0.3688250283,
            "normWar": 1.0,
            "warRank": 1.0,
            "paRank": 1.0,
            "avgRank": 1.0,
            "obpRank": 1.0,
            "slgRank": 3.0,
            "opsRank": 2.0,
            "hrRank": 5.0,
            "kRank": 7.0,
            "bbRank": 3.0,
            "bbpkRank": 5.0,
            "sbpRank": 6.0,
            "sbRank": 2.0,
            "wobaRank": 2.0,
            "contact": 110,
            "gap": 69,
            "power": 71,
            "eye": 82,
            "avoidk": 83,
            "babip": 119,
            "contactvL": 119,
            "gapvL": 69,
            "powervL": 60,
            "eyevL": 111,
            "avoidkvL": 103,
            "babipvL": 122,
            "contactvR": 106,
            "gapvR": 69,
            "powervR": 75,
            "eyevR": 76,
            "avoidkvR": 78,
            "babipvR": 118,
            "gbProfile": 0,
            "fbProfile": 0,
            "batterProfile": 0,
            "speed": 85,
            "stealRate": 62,
            "stealing": 83,
            "baserunning": 104,
            "sacBunt": 64,
            "buntForHit": 55,
            "catchAbil": 0,
            "catchFrame": 0,
            "catchArm": 0,
            "infRange": 103,
            "infError": 69,
            "infArm": 84,
            "dp": 94,
            "outfRange": 61,
            "outfError": 52,
            "outfArm": 87
        },
        {
            "index": 17,
            "cid": 68435,
            "title": "Theme Week - Unsung Heroes 2B Damion Easley DET 2000",
            "value": 72,
            "price": 4190,
            "pa": 4825,
            "war": 2.5740932642,
            "avg": 0.2811038354,
            "obp": 0.352746114,
            "slg": 0.4328811974,
            "ops": 0.7856273114,
            "hr": 11.8134715026,
            "kp": 0.1001036269,
            "bbp": 0.0988601036,
            "bbpk": 0.9875776398,
            "sbp": 0.56,
            "sb": 5.2227979275,
            "woba": 0.3464340602,
            "normWar": 0.9734655765,
            "warRank": 2.0,
            "paRank": 7.0,
            "avgRank": 6.0,
            "obpRank": 3.0,
            "slgRank": 4.0,
            "opsRank": 4.0,
            "hrRank": 4.0,
            "kRank": 5.0,
            "bbRank": 2.0,
            "bbpkRank": 3.0,
            "sbpRank": 8.0,
            "sbRank": 5.0,
            "wobaRank": 4.0,
            "contact": 92,
            "gap": 108,
            "power": 77,
            "eye": 89,
            "avoidk": 96,
            "babip": 80,
            "contactvL": 108,
            "gapvL": 110,
            "powervL": 66,
            "eyevL": 87,
            "avoidkvL": 112,
            "babipvL": 92,
            "contactvR": 86,
            "gapvR": 107,
            "powervR": 81,
            "eyevR": 90,
            "avoidkvR": 91,
            "babipvR": 78,
            "gbProfile": 0,
            "fbProfile": 0,
            "batterProfile": 0,
            "speed": 53,
            "stealRate": 57,
            "stealing": 76,
            "baserunning": 62,
            "sacBunt": 18,
            "buntForHit": 2,
            "catchAbil": 0,
            "catchFrame": 0,
            "catchArm": 0,
            "infRange": 112,
            "infError": 117,
            "infArm": 92,
            "dp": 99,
            "outfRange": 10,
            "outfError": 5,
            "outfArm": 5
        },
        {
            "index": 3,
            "cid": 65678,
            "title": "College Connections: USC - Snapshot SS Roy Smalley MIN 1980",
            "value": 78,
            "price": 238,
            "pa": 40574,
            "war": 2.3054172623,
            "avg": 0.2912823397,
            "obp": 0.3696948785,
            "slg": 0.4901856018,
            "ops": 0.8598804803,
            "hr": 22.8027801055,
            "kp": 0.1239956622,
            "bbp": 0.109429684,
            "bbpk": 0.8825283244,
            "sbp": 0.6166666667,
            "sb": 0.5471484202,
            "woba": 0.3763473335,
            "normWar": 0.9284149808,
            "warRank": 3.0,
            "paRank": 2.0,
            "avgRank": 3.0,
            "obpRank": 2.0,
            "slgRank": 1.0,
            "opsRank": 1.0,
            "hrRank": 1.0,
            "kRank": 8.0,
            "bbRank": 1.0,
            "bbpkRank": 4.0,
            "sbpRank": 4.0,
            "sbRank": 10.0,
            "wobaRank": 1.0,
            "contact": 87,
            "gap": 78,
            "power": 93,
            "eye": 97,
            "avoidk": 87,
            "babip": 80,
            "contactvL": 78,
            "gapvL": 73,
            "powervL": 121,
            "eyevL": 79,
            "avoidkvL": 77,
            "babipvL": 77,
            "contactvR": 91,
            "gapvR": 80,
            "powervR": 84,
            "eyevR": 104,
            "avoidkvR": 92,
            "babipvR": 82,
            "gbProfile": 0,
            "fbProfile": 0,
            "batterProfile": 0,
            "speed": 39,
            "stealRate": 19,
            "stealing": 18,
            "baserunning": 53,
            "sacBunt": 99,
            "buntForHit": 92,
            "catchAbil": 0,
            "catchFrame": 0,
            "catchArm": 0,
            "infRange": 87,
            "infError": 94,
            "infArm": 79,
            "dp": 101,
            "outfRange": 3,
            "outfError": 5,
            "outfArm": 1
        },
        {
            "index": 14,
            "cid": 68039,
            "title": "Theme Week - Snapshot 3B Travis Fryman DET 1997",
            "value": 66,
            "price": 373,
            "pa": 2246,
            "war": 2.2439893143,
            "avg": 0.3005358013,
            "obp": 0.3468388246,
            "slg": 0.4705309303,
            "ops": 0.8173697549,
            "hr": 14.9599287622,
            "kp": 0.124666073,
            "bbp": 0.0667853963,
            "bbpk": 0.5357142857,
            "sbp": 0.6071428571,
            "sb": 4.5414069457,
            "woba": 0.3549465717,
            "normWar": 0.9181149702,
            "warRank": 4.0,
            "paRank": 8.0,
            "avgRank": 2.0,
            "obpRank": 4.0,
            "slgRank": 2.0,
            "opsRank": 3.0,
            "hrRank": 2.0,
            "kRank": 9.0,
            "bbRank": 7.0,
            "bbpkRank": 9.0,
            "sbpRank": 5.0,
            "sbRank": 6.0,
            "wobaRank": 3.0,
            "contact": 92,
            "gap": 85,
            "power": 86,
            "eye": 71,
            "avoidk": 85,
            "babip": 89,
            "contactvL": 96,
            "gapvL": 87,
            "powervL": 80,
            "eyevL": 77,
            "avoidkvL": 83,
            "babipvL": 97,
            "contactvR": 90,
            "gapvR": 84,
            "powervR": 88,
            "eyevR": 69,
            "avoidkvR": 86,
            "babipvR": 86,
            "gbProfile": 0,
            "fbProfile": 0,
            "batterProfile": 0,
            "speed": 68,
            "stealRate": 57,
            "stealing": 84,
            "baserunning": 85,
            "sacBunt": 5,
            "buntForHit": 4,
            "catchAbil": 0,
            "catchFrame": 0,
            "catchArm": 0,
            "infRange": 93,
            "infError": 98,
            "infArm": 92,
            "dp": 85,
            "outfRange": 2,
            "outfError": 7,
            "outfArm": 9
        },
        {
            "index": 16,
            "cid": 65041,
            "title": "T4 Ep. 3 - Unsung Heroes SS Adam Everett HOU 2003",
            "value": 70,
            "price": 382,
            "pa": 14609,
            "war": 1.9138886987,
            "avg": 0.2777903384,
            "obp": 0.3343829146,
            "slg": 0.4229406888,
            "ops": 0.7573236035,
            "hr": 12.9783010473,
            "kp": 0.1273872271,
            "bbp": 0.0768704223,
            "bbpk": 0.6034390113,
            "sbp": 0.6388888889,
            "sb": 6.6123622425,
            "woba": 0.3329156676,
            "normWar": 0.862764923,
            "warRank": 5.0,
            "paRank": 3.0,
            "avgRank": 7.0,
            "obpRank": 6.0,
            "slgRank": 5.0,
            "opsRank": 5.0,
            "hrRank": 3.0,
            "kRank": 10.0,
            "bbRank": 4.0,
            "bbpkRank": 8.0,
            "sbpRank": 3.0,
            "sbRank": 4.0,
            "wobaRank": 5.0,
            "contact": 78,
            "gap": 77,
            "power": 60,
            "eye": 72,
            "avoidk": 80,
            "babip": 75,
            "contactvL": 97,
            "gapvL": 65,
            "powervL": 88,
            "eyevL": 93,
            "avoidkvL": 88,
            "babipvL": 94,
            "contactvR": 75,
            "gapvR": 82,
            "powervR": 53,
            "eyevR": 66,
            "avoidkvR": 79,
            "babipvR": 70,
            "gbProfile": 2,
            "fbProfile": 0,
            "batterProfile": 0,
            "speed": 63,
            "stealRate": 43,
            "stealing": 80,
            "baserunning": 73,
            "sacBunt": 62,
            "buntForHit": 58,
            "catchAbil": 0,
            "catchFrame": 0,
            "catchArm": 0,
            "infRange": 109,
            "infError": 84,
            "infArm": 103,
            "dp": 109,
            "outfRange": 3,
            "outfError": 7,
            "outfArm": 9
        },
        {
            "index": 21,
            "cid": 67164,
            "title": "Theme Week - Unsung Heroes SS Ed Brinkman WS2 1969",
            "value": 68,
            "price": 60,
            "pa": 1933,
            "war": 1.8003103983,
            "avg": 0.2816419612,
            "obp": 0.3362648733,
            "slg": 0.3688711517,
            "ops": 0.7051360249,
            "hr": 1.2415933782,
            "kp": 0.0744956027,
            "bbp": 0.0755302638,
            "bbpk": 1.0138888889,
            "sbp": 0.6666666667,
            "sb": 0.6207966891,
            "woba": 0.3132246377,
            "normWar": 0.8437205347,
            "warRank": 6.0,
            "paRank": 9.0,
            "avgRank": 5.0,
            "obpRank": 5.0,
            "slgRank": 8.0,
            "opsRank": 7.0,
            "hrRank": 10.0,
            "kRank": 2.0,
            "bbRank": 5.0,
            "bbpkRank": 2.0,
            "sbpRank": 2.0,
            "sbRank": 9.0,
            "wobaRank": 7.0,
            "contact": 100,
            "gap": 74,
            "power": 21,
            "eye": 75,
            "avoidk": 117,
            "babip": 78,
            "contactvL": 89,
            "gapvL": 56,
            "powervL": 10,
            "eyevL": 68,
            "avoidkvL": 117,
            "babipvL": 69,
            "contactvR": 103,
            "gapvR": 79,
            "powervR": 25,
            "eyevR": 77,
            "avoidkvR": 117,
            "babipvR": 81,
            "gbProfile": 0,
            "fbProfile": 2,
            "batterProfile": 0,
            "speed": 56,
            "stealRate": 22,
            "stealing": 25,
            "baserunning": 83,
            "sacBunt": 69,
            "buntForHit": 53,
            "catchAbil": 0,
            "catchFrame": 0,
            "catchArm": 0,
            "infRange": 107,
            "infError": 102,
            "infArm": 100,
            "dp": 96,
            "outfRange": 6,
            "outfError": 5,
            "outfArm": 4
        },
        {
            "index": 4,
            "cid": 67162,
            "title": "Theme Week - Rookie Sensation 2B Ted Sizemore LAD 1969",
            "value": 70,
            "price": 746,
            "pa": 11365,
            "war": 0.6757589089,
            "avg": 0.2862264151,
            "obp": 0.3239771227,
            "slg": 0.3954716981,
            "ops": 0.7194488209,
            "hr": 4.0651121865,
            "kp": 0.0452265728,
            "bbp": 0.0522657281,
            "bbpk": 1.1556420233,
            "sbp": 0.5092592593,
            "sb": 2.9036515618,
            "woba": 0.3163536983,
            "normWar": 0.6551599107,
            "warRank": 7.0,
            "paRank": 4.0,
            "avgRank": 4.0,
            "obpRank": 7.0,
            "slgRank": 6.0,
            "opsRank": 6.0,
            "hrRank": 7.0,
            "kRank": 1.0,
            "bbRank": 9.0,
            "bbpkRank": 1.0,
            "sbpRank": 9.0,
            "sbRank": 8.0,
            "wobaRank": 6.0,
            "contact": 106,
            "gap": 77,
            "power": 31,
            "eye": 64,
            "avoidk": 153,
            "babip": 75,
            "contactvL": 125,
            "gapvL": 77,
            "powervL": 30,
            "eyevL": 59,
            "avoidkvL": 166,
            "babipvL": 91,
            "contactvR": 100,
            "gapvR": 77,
            "powervR": 32,
            "eyevR": 66,
            "avoidkvR": 148,
            "babipvR": 71,
            "gbProfile": 0,
            "fbProfile": 0,
            "batterProfile": 0,
            "speed": 54,
            "stealRate": 31,
            "stealing": 58,
            "baserunning": 58,
            "sacBunt": 34,
            "buntForHit": 3,
            "catchAbil": 0,
            "catchFrame": 0,
            "catchArm": 0,
            "infRange": 104,
            "infError": 93,
            "infArm": 84,
            "dp": 102,
            "outfRange": 4,
            "outfError": 5,
            "outfArm": 10
        },
        {
            "index": 20,
            "cid": 63218,
            "title": "Snapshot SS Wayne Causey KC1 1963",
            "value": 79,
            "price": 246,
            "pa": 5560,
            "war": -1.3273381295,
            "avg": 0.2617687611,
            "obp": 0.3167266187,
            "slg": 0.3730549537,
            "ops": 0.6897815724,
            "hr": 6.1510791367,
            "kp": 0.1019784173,
            "bbp": 0.0714028777,
            "bbpk": 0.7001763668,
            "sbp": 0.5,
            "sb": 3.4532374101,
            "woba": 0.3059711971,
            "normWar": 0.3192880267,
            "warRank": 8.0,
            "paRank": 5.0,
            "avgRank": 8.0,
            "obpRank": 8.0,
            "slgRank": 7.0,
            "opsRank": 8.0,
            "hrRank": 6.0,
            "kRank": 6.0,
            "bbRank": 6.0,
            "bbpkRank": 7.0,
            "sbpRank": 10.0,
            "sbRank": 7.0,
            "wobaRank": 8.0,
            "contact": 79,
            "gap": 89,
            "power": 39,
            "eye": 70,
            "avoidk": 99,
            "babip": 67,
            "contactvL": 77,
            "gapvL": 100,
            "powervL": 33,
            "eyevL": 83,
            "avoidkvL": 92,
            "babipvL": 67,
            "contactvR": 79,
            "gapvR": 85,
            "powervR": 42,
            "eyevR": 66,
            "avoidkvR": 101,
            "babipvR": 67,
            "gbProfile": 1,
            "fbProfile": 0,
            "batterProfile": 0,
            "speed": 35,
            "stealRate": 21,
            "stealing": 65,
            "baserunning": 35,
            "sacBunt": 25,
            "buntForHit": 9,
            "catchAbil": 0,
            "catchFrame": 0,
            "catchArm": 0,
            "infRange": 72,
            "infError": 92,
            "infArm": 75,
            "dp": 70,
            "outfRange": 3,
            "outfError": 9,
            "outfArm": 6
        },
        {
            "index": 9,
            "cid": 63240,
            "title": "Snapshot SS Sonny Jackson HOU 1966",
            "value": 79,
            "price": 296,
            "pa": 778,
            "war": -2.7763496144,
            "avg": 0.2454672245,
            "obp": 0.2956298201,
            "slg": 0.2747559275,
            "ops": 0.5703857475,
            "hr": 2.3136246787,
            "kp": 0.0861182519,
            "bbp": 0.0629820051,
            "bbpk": 0.7313432836,
            "sbp": 0.8,
            "sb": 12.3393316195,
            "woba": 0.2599100257,
            "normWar": 0.0763231537,
            "warRank": 9.0,
            "paRank": 10.0,
            "avgRank": 10.0,
            "obpRank": 9.0,
            "slgRank": 10.0,
            "opsRank": 10.0,
            "hrRank": 9.0,
            "kRank": 3.0,
            "bbRank": 8.0,
            "bbpkRank": 6.0,
            "sbpRank": 1.0,
            "sbRank": 1.0,
            "wobaRank": 10.0,
            "contact": 86,
            "gap": 25,
            "power": 19,
            "eye": 65,
            "avoidk": 101,
            "babip": 74,
            "contactvL": 79,
            "gapvL": 28,
            "powervL": 19,
            "eyevL": 77,
            "avoidkvL": 85,
            "babipvL": 74,
            "contactvR": 90,
            "gapvR": 23,
            "powervR": 20,
            "eyevR": 61,
            "avoidkvR": 107,
            "babipvR": 74,
            "gbProfile": 0,
            "fbProfile": 0,
            "batterProfile": 0,
            "speed": 79,
            "stealRate": 83,
            "stealing": 82,
            "baserunning": 76,
            "sacBunt": 94,
            "buntForHit": 10,
            "catchAbil": 0,
            "catchFrame": 0,
            "catchArm": 0,
            "infRange": 96,
            "infError": 49,
            "infArm": 82,
            "dp": 80,
            "outfRange": 7,
            "outfError": 10,
            "outfArm": 10
        },
        {
            "index": 26,
            "cid": 59334,
            "title": "Snapshot SS Bob Bailor TOR 1977",
            "value": 79,
            "price": 196,
            "pa": 4846,
            "war": -3.2315311597,
            "avg": 0.2489224138,
            "obp": 0.2719768882,
            "slg": 0.3163793103,
            "ops": 0.5883561985,
            "hr": 3.9620305407,
            "kp": 0.0870821296,
            "bbp": 0.0276516715,
            "bbpk": 0.317535545,
            "sbp": 0.5631067961,
            "sb": 7.1811803549,
            "woba": 0.2603673891,
            "normWar": 0.0,
            "warRank": 10.0,
            "paRank": 6.0,
            "avgRank": 9.0,
            "obpRank": 10.0,
            "slgRank": 9.0,
            "opsRank": 9.0,
            "hrRank": 8.0,
            "kRank": 4.0,
            "bbRank": 10.0,
            "bbpkRank": 10.0,
            "sbpRank": 7.0,
            "sbRank": 3.0,
            "wobaRank": 9.0,
            "contact": 90,
            "gap": 52,
            "power": 31,
            "eye": 44,
            "avoidk": 111,
            "babip": 73,
            "contactvL": 99,
            "gapvL": 47,
            "powervL": 37,
            "eyevL": 39,
            "avoidkvL": 133,
            "babipvL": 73,
            "contactvR": 88,
            "gapvR": 53,
            "powervR": 29,
            "eyevR": 46,
            "avoidkvR": 106,
            "babipvR": 73,
            "gbProfile": 0,
            "fbProfile": 2,
            "batterProfile": 0,
            "speed": 67,
            "stealRate": 61,
            "stealing": 73,
            "baserunning": 73,
            "sacBunt": 26,
            "buntForHit": 1,
            "catchAbil": 0,
            "catchFrame": 0,
            "catchArm": 0,
            "infRange": 82,
            "infError": 73,
            "infArm": 77,
            "dp": 73,
            "outfRange": 74,
            "outfError": 44,
            "outfArm": 120
        }
    ]
}