{
    "starting_pitchers": [
        {
            "index": 0,
            "cid": 65407,
            "title": "T4 Ep. 9 - Snapshot SP Deacon Phillippe PIT 1903",
            "fip": 4.12,
            "war": 4.29,
            "ipc": 20862.67,
            "ipg": 6.78,
            "w": 1292,
            "l": 1012,
            "wpct": 0.56,
            "era": 4.15,
            "kp9": 2.74,
            "bbp9": 1.95,
            "hrp9": 0.48,
            "qspct": 0.5,
            "gbrate": 0.47,
            "fipRank": 1.0,
            "warRank": 1.0,
            "wpctRank": 2.0,
            "eraRank": 1.0,
            "kRank": 10.0,
            "bbRank": 2.0,
            "hrRank": 11.0,
            "qsRank": 1.0,
            "gbRateRank": 13.0,
            "stuff": 66,
            "movement": 86,
            "control": 145,
            "pHR": 91,
            "pBabip": 85,
            "stuffvL": 66,
            "movementvL": 86,
            "controlvL": 146,
            "pHRvL": 90,
            "pBabipvL": 87,
            "stuffvR": 65,
            "movementvR": 86,
            "controlvR": 144,
            "pHRvR": 92,
            "pBabipvR": 84,
            "fastball": 76,
            "slider": 0,
            "curveball": 79,
            "changeup": 78,
            "cutter": 0,
            "sinker": 0,
            "splitter": 0,
            "forkball": 0,
            "screwball": 0,
            "circlechange": 0,
            "knucklecurve": 0,
            "knuckleball": 0,
            "stamina": 86,
            "hold": 74,
            "gb": 2,
            "velocity": "89-91",
            "armSlot": 3
        },
        {
            "index": 1,
            "cid": 62152,
            "title": "Unsung Heroes SP Earl Yingling BRO 1913",
            "fip": 4.16,
            "war": 3.83,
            "ipc": 438.33,
            "ipg": 4.14,
            "w": 17,
            "l": 24,
            "wpct": 0.41,
            "era": 4.46,
            "kp9": 1.85,
            "bbp9": 1.23,
            "hrp9": 0.55,
            "qspct": 0.4,
            "gbrate": 0.48,
            "fipRank": 2.0,
            "warRank": 2.0,
            "wpctRank": 16.0,
            "eraRank": 5.0,
            "kRank": 14.0,
            "bbRank": 1.0,
            "hrRank": 13.0,
            "qsRank": 13.0,
            "gbRateRank": 10.0,
            "stuff": 34,
            "movement": 72,
            "control": 156,
            "pHR": 72,
            "pBabip": 66,
            "stuffvL": 34,
            "movementvL": 72,
            "controlvL": 156,
            "pHRvL": 72,
            "pBabipvL": 66,
            "stuffvR": 34,
            "movementvR": 72,
            "controlvR": 156,
            "pHRvR": 72,
            "pBabipvR": 66,
            "fastball": 23,
            "slider": 20,
            "curveball": 25,
            "changeup": 23,
            "cutter": 0,
            "sinker": 0,
            "splitter": 0,
            "forkball": 0,
            "screwball": 0,
            "circlechange": 0,
            "knucklecurve": 0,
            "knuckleball": 0,
            "stamina": 103,
            "hold": 67,
            "gb": 2,
            "velocity": "89-91",
            "armSlot": 4
        },
        {
            "index": 2,
            "cid": 65115,
            "title": "Tournament Edition 4 SP Ed Morris PIT 1888",
            "fip": 4.37,
            "war": 3.52,
            "ipc": 437.0,
            "ipg": 5.53,
            "w": 22,
            "l": 28,
            "wpct": 0.44,
            "era": 4.55,
            "kp9": 1.63,
            "bbp9": 2.97,
            "hrp9": 0.25,
            "qspct": 0.43,
            "gbrate": 0.49,
            "fipRank": 3.0,
            "warRank": 3.0,
            "wpctRank": 15.0,
            "eraRank": 7.0,
            "kRank": 16.0,
            "bbRank": 6.0,
            "hrRank": 2.0,
            "qsRank": 7.0,
            "gbRateRank": 6.0,
            "stuff": 38,
            "movement": 92,
            "control": 126,
            "pHR": 115,
            "pBabip": 69,
            "stuffvL": 38,
            "movementvL": 93,
            "controlvL": 131,
            "pHRvL": 119,
            "pBabipvL": 68,
            "stuffvR": 38,
            "movementvR": 92,
            "controlvR": 124,
            "pHRvR": 114,
            "pBabipvR": 70,
            "fastball": 29,
            "slider": 0,
            "curveball": 29,
            "changeup": 28,
            "cutter": 0,
            "sinker": 0,
            "splitter": 0,
            "forkball": 0,
            "screwball": 0,
            "circlechange": 0,
            "knucklecurve": 0,
            "knuckleball": 0,
            "stamina": 105,
            "hold": 81,
            "gb": 2,
            "velocity": "90-92",
            "armSlot": 3
        },
        {
            "index": 3,
            "cid": 64763,
            "title": "T4 Ep. 21 - Negro League Star SP Jose Suarez Cincinnati Cuban Stars 1921",
            "fip": 4.39,
            "war": 3.47,
            "ipc": 1234.0,
            "ipg": 5.02,
            "w": 66,
            "l": 71,
            "wpct": 0.48,
            "era": 4.51,
            "kp9": 2.79,
            "bbp9": 2.95,
            "hrp9": 0.45,
            "qspct": 0.46,
            "gbrate": 0.49,
            "fipRank": 4.0,
            "warRank": 4.0,
            "wpctRank": 10.0,
            "eraRank": 6.0,
            "kRank": 8.0,
            "bbRank": 5.0,
            "hrRank": 8.0,
            "qsRank": 2.0,
            "gbRateRank": 7.0,
            "stuff": 75,
            "movement": 79,
            "control": 115,
            "pHR": 111,
            "pBabip": 58,
            "stuffvL": 72,
            "movementvL": 77,
            "controlvL": 120,
            "pHRvL": 110,
            "pBabipvL": 57,
            "stuffvR": 76,
            "movementvR": 79,
            "controlvR": 112,
            "pHRvR": 113,
            "pBabipvR": 59,
            "fastball": 77,
            "slider": 77,
            "curveball": 0,
            "changeup": 74,
            "cutter": 0,
            "sinker": 0,
            "splitter": 74,
            "forkball": 0,
            "screwball": 0,
            "circlechange": 0,
            "knucklecurve": 0,
            "knuckleball": 0,
            "stamina": 96,
            "hold": 84,
            "gb": 2,
            "velocity": "90-92",
            "armSlot": 3
        },
        {
            "index": 4,
            "cid": 65545,
            "title": "T4 Ep. 7 - Snapshot SP Sam Leever PIT 1904",
            "fip": 4.47,
            "war": 3.39,
            "ipc": 16124.67,
            "ipg": 6.29,
            "w": 1012,
            "l": 813,
            "wpct": 0.55,
            "era": 4.29,
            "kp9": 1.76,
            "bbp9": 2.34,
            "hrp9": 0.48,
            "qspct": 0.46,
            "gbrate": 0.49,
            "fipRank": 5.0,
            "warRank": 5.0,
            "wpctRank": 4.0,
            "eraRank": 2.0,
            "kRank": 15.0,
            "bbRank": 3.0,
            "hrRank": 12.0,
            "qsRank": 3.0,
            "gbRateRank": 8.0,
            "stuff": 37,
            "movement": 98,
            "control": 132,
            "pHR": 94,
            "pBabip": 112,
            "stuffvL": 37,
            "movementvL": 97,
            "controlvL": 135,
            "pHRvL": 92,
            "pBabipvL": 114,
            "stuffvR": 37,
            "movementvR": 98,
            "controlvR": 130,
            "pHRvR": 96,
            "pBabipvR": 110,
            "fastball": 29,
            "slider": 0,
            "curveball": 31,
            "changeup": 31,
            "cutter": 0,
            "sinker": 0,
            "splitter": 0,
            "forkball": 0,
            "screwball": 0,
            "circlechange": 0,
            "knucklecurve": 0,
            "knuckleball": 0,
            "stamina": 99,
            "hold": 75,
            "gb": 2,
            "velocity": "89-91",
            "armSlot": 3
        },
        {
            "index": 5,
            "cid": 68008,
            "title": "Tournament Edition 4 SP Silver King SL4 1887",
            "fip": 4.61,
            "war": 3.05,
            "ipc": 8634.67,
            "ipg": 6.28,
            "w": 540,
            "l": 426,
            "wpct": 0.56,
            "era": 4.37,
            "kp9": 2.85,
            "bbp9": 4.32,
            "hrp9": 0.28,
            "qspct": 0.46,
            "gbrate": 0.46,
            "fipRank": 6.0,
            "warRank": 6.0,
            "wpctRank": 3.0,
            "eraRank": 4.0,
            "kRank": 7.0,
            "bbRank": 11.0,
            "hrRank": 3.0,
            "qsRank": 4.0,
            "gbRateRank": 15.0,
            "stuff": 78,
            "movement": 113,
            "control": 91,
            "pHR": 121,
            "pBabip": 119,
            "stuffvL": 78,
            "movementvL": 113,
            "controlvL": 87,
            "pHRvL": 118,
            "pBabipvL": 121,
            "stuffvR": 77,
            "movementvR": 114,
            "controlvR": 94,
            "pHRvR": 125,
            "pBabipvR": 117,
            "fastball": 79,
            "slider": 0,
            "curveball": 92,
            "changeup": 84,
            "cutter": 0,
            "sinker": 0,
            "splitter": 0,
            "forkball": 0,
            "screwball": 0,
            "circlechange": 0,
            "knucklecurve": 0,
            "knuckleball": 0,
            "stamina": 111,
            "hold": 55,
            "gb": 3,
            "velocity": "90-92",
            "armSlot": 3
        },
        {
            "index": 6,
            "cid": 65947,
            "title": "Tournament Edition 3 SP Lon Warneke CHC 1936",
            "fip": 4.62,
            "war": 2.84,
            "ipc": 3826.67,
            "ipg": 4.18,
            "w": 221,
            "l": 219,
            "wpct": 0.5,
            "era": 4.61,
            "kp9": 3.21,
            "bbp9": 4.45,
            "hrp9": 0.31,
            "qspct": 0.45,
            "gbrate": 0.5,
            "fipRank": 7.0,
            "warRank": 9.0,
            "wpctRank": 7.0,
            "eraRank": 8.0,
            "kRank": 1.0,
            "bbRank": 12.0,
            "hrRank": 4.0,
            "qsRank": 5.0,
            "gbRateRank": 1.0,
            "stuff": 91,
            "movement": 91,
            "control": 89,
            "pHR": 112,
            "pBabip": 70,
            "stuffvL": 94,
            "movementvL": 91,
            "controlvL": 81,
            "pHRvL": 109,
            "pBabipvL": 73,
            "stuffvR": 89,
            "movementvR": 91,
            "controlvR": 96,
            "pHRvR": 114,
            "pBabipvR": 68,
            "fastball": 80,
            "slider": 0,
            "curveball": 102,
            "changeup": 81,
            "cutter": 0,
            "sinker": 0,
            "splitter": 0,
            "forkball": 0,
            "screwball": 81,
            "circlechange": 0,
            "knucklecurve": 0,
            "knuckleball": 0,
            "stamina": 103,
            "hold": 115,
            "gb": 2,
            "velocity": "90-92",
            "armSlot": 3
        },
        {
            "index": 7,
            "cid": 65579,
            "title": "Early Eras - Snapshot SP Noodles Hahn CIN 1904",
            "fip": 4.67,
            "war": 2.86,
            "ipc": 7999.0,
            "ipg": 4.79,
            "w": 427,
            "l": 486,
            "wpct": 0.47,
            "era": 4.72,
            "kp9": 2.47,
            "bbp9": 3.57,
            "hrp9": 0.45,
            "qspct": 0.43,
            "gbrate": 0.5,
            "fipRank": 8.0,
            "warRank": 7.0,
            "wpctRank": 11.0,
            "eraRank": 10.0,
            "kRank": 11.0,
            "bbRank": 7.0,
            "hrRank": 9.0,
            "qsRank": 8.0,
            "gbRateRank": 2.0,
            "stuff": 54,
            "movement": 84,
            "control": 105,
            "pHR": 81,
            "pBabip": 93,
            "stuffvL": 55,
            "movementvL": 89,
            "controlvL": 112,
            "pHRvL": 87,
            "pBabipvL": 98,
            "stuffvR": 54,
            "movementvR": 82,
            "controlvR": 103,
            "pHRvR": 79,
            "pBabipvR": 91,
            "fastball": 52,
            "slider": 44,
            "curveball": 0,
            "changeup": 55,
            "cutter": 0,
            "sinker": 0,
            "splitter": 0,
            "forkball": 0,
            "screwball": 0,
            "circlechange": 0,
            "knucklecurve": 0,
            "knuckleball": 0,
            "stamina": 114,
            "hold": 69,
            "gb": 2,
            "velocity": "90-92",
            "armSlot": 4
        },
        {
            "index": 8,
            "cid": 65896,
            "title": "T4 Ep. 7 - All-Star SP Red Ruffing NYY 1939",
            "fip": 4.69,
            "war": 2.79,
            "ipc": 4240.33,
            "ipg": 4.93,
            "w": 215,
            "l": 243,
            "wpct": 0.47,
            "era": 4.92,
            "kp9": 3.21,
            "bbp9": 2.66,
            "hrp9": 0.78,
            "qspct": 0.4,
            "gbrate": 0.41,
            "fipRank": 9.0,
            "warRank": 10.0,
            "wpctRank": 12.0,
            "eraRank": 15.0,
            "kRank": 2.0,
            "bbRank": 4.0,
            "hrRank": 16.0,
            "qsRank": 14.0,
            "gbRateRank": 16.0,
            "stuff": 98,
            "movement": 72,
            "control": 128,
            "pHR": 70,
            "pBabip": 70,
            "stuffvL": 96,
            "movementvL": 72,
            "controlvL": 127,
            "pHRvL": 71,
            "pBabipvL": 68,
            "stuffvR": 101,
            "movementvR": 72,
            "controlvR": 129,
            "pHRvR": 69,
            "pBabipvR": 72,
            "fastball": 102,
            "slider": 87,
            "curveball": 111,
            "changeup": 0,
            "cutter": 0,
            "sinker": 0,
            "splitter": 0,
            "forkball": 0,
            "screwball": 0,
            "circlechange": 0,
            "knucklecurve": 0,
            "knuckleball": 0,
            "stamina": 99,
            "hold": 115,
            "gb": 4,
            "velocity": "89-91",
            "armSlot": 4
        },
        {
            "index": 9,
            "cid": 66123,
            "title": "T4 Ep. 21 - Snapshot SP Ice Box Chamberlain LS3 Peak",
            "fip": 4.73,
            "war": 2.85,
            "ipc": 5439.0,
            "ipg": 6.57,
            "w": 314,
            "l": 268,
            "wpct": 0.54,
            "era": 4.34,
            "kp9": 3.0,
            "bbp9": 4.54,
            "hrp9": 0.35,
            "qspct": 0.45,
            "gbrate": 0.48,
            "fipRank": 10.0,
            "warRank": 8.0,
            "wpctRank": 6.0,
            "eraRank": 3.0,
            "kRank": 5.0,
            "bbRank": 13.0,
            "hrRank": 5.0,
            "qsRank": 6.0,
            "gbRateRank": 11.0,
            "stuff": 93,
            "movement": 113,
            "control": 86,
            "pHR": 114,
            "pBabip": 127,
            "stuffvL": 89,
            "movementvL": 108,
            "controlvL": 85,
            "pHRvL": 109,
            "pBabipvL": 120,
            "stuffvR": 96,
            "movementvR": 117,
            "controlvR": 88,
            "pHRvR": 117,
            "pBabipvR": 133,
            "fastball": 97,
            "slider": 0,
            "curveball": 0,
            "changeup": 103,
            "cutter": 0,
            "sinker": 92,
            "splitter": 0,
            "forkball": 0,
            "screwball": 0,
            "circlechange": 0,
            "knucklecurve": 0,
            "knuckleball": 0,
            "stamina": 112,
            "hold": 59,
            "gb": 2,
            "velocity": "89-91",
            "armSlot": 3
        },
        {
            "index": 10,
            "cid": 65481,
            "title": "T4 Ep. 2 - Snapshot SP Ray Caldwell NYY 1918",
            "fip": 4.77,
            "war": 2.52,
            "ipc": 2357.33,
            "ipg": 5.36,
            "w": 147,
            "l": 110,
            "wpct": 0.57,
            "era": 4.77,
            "kp9": 3.05,
            "bbp9": 4.61,
            "hrp9": 0.37,
            "qspct": 0.41,
            "gbrate": 0.47,
            "fipRank": 11.0,
            "warRank": 11.0,
            "wpctRank": 1.0,
            "eraRank": 13.0,
            "kRank": 3.0,
            "bbRank": 14.0,
            "hrRank": 6.0,
            "qsRank": 11.0,
            "gbRateRank": 14.0,
            "stuff": 77,
            "movement": 74,
            "control": 78,
            "pHR": 102,
            "pBabip": 54,
            "stuffvL": 79,
            "movementvL": 74,
            "controlvL": 72,
            "pHRvL": 99,
            "pBabipvL": 55,
            "stuffvR": 76,
            "movementvR": 74,
            "controlvR": 84,
            "pHRvR": 105,
            "pBabipvR": 53,
            "fastball": 80,
            "slider": 0,
            "curveball": 0,
            "changeup": 73,
            "cutter": 0,
            "sinker": 0,
            "splitter": 0,
            "forkball": 0,
            "screwball": 92,
            "circlechange": 0,
            "knucklecurve": 0,
            "knuckleball": 0,
            "stamina": 79,
            "hold": 86,
            "gb": 3,
            "velocity": "90-92",
            "armSlot": 4
        },
        {
            "index": 11,
            "cid": 67959,
            "title": "Happy Holidays - Snapshot SP George Winter BOS 1907",
            "fip": 4.84,
            "war": 2.26,
            "ipc": 4480.67,
            "ipg": 4.66,
            "w": 271,
            "l": 221,
            "wpct": 0.55,
            "era": 4.63,
            "kp9": 2.3,
            "bbp9": 3.9,
            "hrp9": 0.46,
            "qspct": 0.43,
            "gbrate": 0.49,
            "fipRank": 12.0,
            "warRank": 14.0,
            "wpctRank": 5.0,
            "eraRank": 9.0,
            "kRank": 12.0,
            "bbRank": 9.0,
            "hrRank": 10.0,
            "qsRank": 9.0,
            "gbRateRank": 9.0,
            "stuff": 60,
            "movement": 112,
            "control": 97,
            "pHR": 101,
            "pBabip": 143,
            "stuffvL": 60,
            "movementvL": 111,
            "controlvL": 99,
            "pHRvL": 99,
            "pBabipvL": 142,
            "stuffvR": 61,
            "movementvR": 114,
            "controlvR": 96,
            "pHRvR": 104,
            "pBabipvR": 144,
            "fastball": 68,
            "slider": 68,
            "curveball": 64,
            "changeup": 0,
            "cutter": 0,
            "sinker": 0,
            "splitter": 0,
            "forkball": 0,
            "screwball": 68,
            "circlechange": 0,
            "knucklecurve": 0,
            "knuckleball": 0,
            "stamina": 109,
            "hold": 60,
            "gb": 2,
            "velocity": "88-90",
            "armSlot": 3
        },
        {
            "index": 12,
            "cid": 65413,
            "title": "T4 Ep. 19 - Snapshot SP Cy Falkenberg CLE 1909",
            "fip": 4.86,
            "war": 2.49,
            "ipc": 3430.0,
            "ipg": 4.96,
            "w": 181,
            "l": 212,
            "wpct": 0.46,
            "era": 4.88,
            "kp9": 2.98,
            "bbp9": 5.45,
            "hrp9": 0.23,
            "qspct": 0.39,
            "gbrate": 0.5,
            "fipRank": 13.0,
            "warRank": 12.0,
            "wpctRank": 13.0,
            "eraRank": 14.0,
            "kRank": 6.0,
            "bbRank": 16.0,
            "hrRank": 1.0,
            "qsRank": 16.0,
            "gbRateRank": 3.0,
            "stuff": 86,
            "movement": 108,
            "control": 72,
            "pHR": 139,
            "pBabip": 91,
            "stuffvL": 87,
            "movementvL": 109,
            "controlvL": 71,
            "pHRvL": 144,
            "pBabipvL": 92,
            "stuffvR": 86,
            "movementvR": 107,
            "controlvR": 74,
            "pHRvR": 136,
            "pBabipvR": 91,
            "fastball": 80,
            "slider": 0,
            "curveball": 0,
            "changeup": 84,
            "cutter": 0,
            "sinker": 0,
            "splitter": 0,
            "forkball": 0,
            "screwball": 0,
            "circlechange": 0,
            "knucklecurve": 0,
            "knuckleball": 98,
            "stamina": 84,
            "hold": 69,
            "gb": 2,
            "velocity": "90-92",
            "armSlot": 3
        },
        {
            "index": 13,
            "cid": 65408,
            "title": "T4 Ep. 17 - Snapshot SP George Uhle CLE 1924",
            "fip": 4.9,
            "war": 2.37,
            "ipc": 7274.33,
            "ipg": 5.63,
            "w": 401,
            "l": 416,
            "wpct": 0.49,
            "era": 4.75,
            "kp9": 2.79,
            "bbp9": 4.83,
            "hrp9": 0.37,
            "qspct": 0.41,
            "gbrate": 0.5,
            "fipRank": 14.0,
            "warRank": 13.0,
            "wpctRank": 9.0,
            "eraRank": 11.0,
            "kRank": 9.0,
            "bbRank": 15.0,
            "hrRank": 7.0,
            "qsRank": 12.0,
            "gbRateRank": 4.0,
            "stuff": 79,
            "movement": 97,
            "control": 90,
            "pHR": 109,
            "pBabip": 90,
            "stuffvL": 60,
            "movementvL": 88,
            "controlvL": 69,
            "pHRvL": 96,
            "pBabipvL": 83,
            "stuffvR": 102,
            "movementvR": 105,
            "controlvR": 114,
            "pHRvR": 120,
            "pBabipvR": 95,
            "fastball": 74,
            "slider": 94,
            "curveball": 79,
            "changeup": 0,
            "cutter": 0,
            "sinker": 0,
            "splitter": 0,
            "forkball": 0,
            "screwball": 0,
            "circlechange": 0,
            "knucklecurve": 0,
            "knuckleball": 0,
            "stamina": 107,
            "hold": 84,
            "gb": 2,
            "velocity": "90-92",
            "armSlot": 3
        },
        {
            "index": 14,
            "cid": 65567,
            "title": "Tournament Edition 3 SP Leon Cadore BRO 1917",
            "fip": 4.94,
            "war": 2.2,
            "ipc": 3530.0,
            "ipg": 4.89,
            "w": 201,
            "l": 233,
            "wpct": 0.46,
            "era": 5.04,
            "kp9": 3.02,
            "bbp9": 4.11,
            "hrp9": 0.59,
            "qspct": 0.4,
            "gbrate": 0.5,
            "fipRank": 15.0,
            "warRank": 15.0,
            "wpctRank": 14.0,
            "eraRank": 16.0,
            "kRank": 4.0,
            "bbRank": 10.0,
            "hrRank": 14.0,
            "qsRank": 15.0,
            "gbRateRank": 5.0,
            "stuff": 86,
            "movement": 84,
            "control": 97,
            "pHR": 89,
            "pBabip": 82,
            "stuffvL": 82,
            "movementvL": 80,
            "controlvL": 91,
            "pHRvL": 85,
            "pBabipvL": 77,
            "stuffvR": 89,
            "movementvR": 87,
            "controlvR": 103,
            "pHRvR": 92,
            "pBabipvR": 86,
            "fastball": 83,
            "slider": 0,
            "curveball": 99,
            "changeup": 90,
            "cutter": 0,
            "sinker": 0,
            "splitter": 0,
            "forkball": 0,
            "screwball": 0,
            "circlechange": 0,
            "knucklecurve": 0,
            "knuckleball": 0,
            "stamina": 102,
            "hold": 79,
            "gb": 2,
            "velocity": "89-91",
            "armSlot": 2
        },
        {
            "index": 15,
            "cid": 67728,
            "title": "T4 Ep. 13 - Snapshot SP Bob Caruthers BR3 1888",
            "fip": 5.06,
            "war": 1.99,
            "ipc": 7691.67,
            "ipg": 5.44,
            "w": 407,
            "l": 407,
            "wpct": 0.5,
            "era": 4.76,
            "kp9": 2.2,
            "bbp9": 3.6,
            "hrp9": 0.66,
            "qspct": 0.42,
            "gbrate": 0.48,
            "fipRank": 16.0,
            "warRank": 16.0,
            "wpctRank": 8.0,
            "eraRank": 12.0,
            "kRank": 13.0,
            "bbRank": 8.0,
            "hrRank": 15.0,
            "qsRank": 10.0,
            "gbRateRank": 12.0,
            "stuff": 49,
            "movement": 89,
            "control": 106,
            "pHR": 82,
            "pBabip": 104,
            "stuffvL": 45,
            "movementvL": 79,
            "controlvL": 102,
            "pHRvL": 76,
            "pBabipvL": 90,
            "stuffvR": 52,
            "movementvR": 98,
            "controlvR": 109,
            "pHRvR": 91,
            "pBabipvR": 116,
            "fastball": 46,
            "slider": 0,
            "curveball": 0,
            "changeup": 48,
            "cutter": 0,
            "sinker": 40,
            "splitter": 0,
            "forkball": 0,
            "screwball": 0,
            "circlechange": 0,
            "knucklecurve": 0,
            "knuckleball": 0,
            "stamina": 113,
            "hold": 60,
            "gb": 2,
            "velocity": "89-91",
            "armSlot": 2
        }
    ]
}